cf_changelog/__init__.py
cf_changelog/cf_changelog.py
cf_changelog-1.0.6.dist-info/LICENSE
cf_changelog-1.0.6.dist-info/METADATA
cf_changelog-1.0.6.dist-info/WHEEL
cf_changelog-1.0.6.dist-info/entry_points.txt
cf_changelog-1.0.6.dist-info/top_level.txt
cf_changelog-1.0.6.dist-info/RECORD
