Metadata-Version: 2.1
Name: cf-changelog
Version: 1.0.6
Summary: Conflict-Free Changelog manager
Home-page: https://gitlab.com/salekpawel/cf_changelog
Author: Paweł Sałek
Author-email: salekpawel@gmail.com
License: MIT
License-File: LICENSE
Requires-Dist: GitPython (>=3.1.0)
Requires-Dist: pyyaml (>=6.0)
Requires-Dist: schema (>=0.7.0)
